pyconmech.cp37-win_amd64.pyd
pyconmech-0.1.1.dist-info/LICENSE
pyconmech-0.1.1.dist-info/METADATA
pyconmech-0.1.1.dist-info/WHEEL
pyconmech-0.1.1.dist-info/top_level.txt
pyconmech-0.1.1.dist-info/RECORD
